elastory/exceptions.py
elastory/network/network.py
elastory/plot/network.py
elastory/plot/plotly/utils.py
elastory/plot/utils.py
elastory/response/config.py
elastory/response/data.py
elastory/response/matrix.py
elastory/response/observables.py
elastory/response/optimizer.py
elastory/response/qopt.py
elastory/utils/conversion.py
elastory/utils/f_calculate_rmsd.py
elastory/utils/hessian.py
elastory/utils/matrix.py
elastory/utils/misc.py
elastory/utils/network_tools.py
elastory/utils/repulsive.py
elastory-0.1.0.dist-info/LICENSE
elastory-0.1.0.dist-info/METADATA
elastory-0.1.0.dist-info/WHEEL
elastory-0.1.0.dist-info/RECORD
