Metadata-Version: 2.1
Name: elastory
Version: 0.1.0
Summary: Tools for studying long ranged —allosteric— effects in elastic networks (e.g. of proteins) on a mechanical basis.
Home-page: https://github.com/maxvossel/elastory
License: MIT
Keywords: physics,biophysics,allostery,elastic networks,proteins,computational biology
Author: Maximilian Alexander Vossel
Author-email: mvossel@pm.me
Requires-Python: >=3.11,<4.0
Classifier: License :: OSI Approved :: MIT License
Classifier: Programming Language :: Python :: 3
Classifier: Programming Language :: Python :: 3.11
Classifier: Programming Language :: Python :: 3.12
Requires-Dist: biopython (>=1.85,<2.0)
Requires-Dist: dcor (>=0.6,<0.7)
Requires-Dist: fastdtw (>=0.3.4,<0.4.0)
Requires-Dist: h5py (>=3.13.0,<4.0.0)
Requires-Dist: ipykernel (>=6.29.2,<7.0.0)
Requires-Dist: ipywidgets (>=8.1.7,<9.0.0)
Requires-Dist: jupyterthemes (>=0.20.0,<0.21.0)
Requires-Dist: kaleido (==0.2.1)
Requires-Dist: matplotlib (>=3.10.3,<4.0.0)
Requires-Dist: networkx (>=3.4.2,<4.0.0)
Requires-Dist: numba (>=0.61.2,<0.62.0)
Requires-Dist: numpy (>=2.2.6,<3.0.0)
Requires-Dist: pandas (>=2.0.3,<3.0.0)
Requires-Dist: parmap (>=1.7.0,<2.0.0)
Requires-Dist: pillow (>=11.2.1,<12.0.0)
Requires-Dist: plotly (>=6.1.0,<7.0.0)
Requires-Dist: pre-commit (>=4.2.0,<5.0.0)
Requires-Dist: pydantic (>=2.11.4,<3.0.0)
Requires-Dist: rmsd (>=1.6.4,<2.0.0)
Requires-Dist: ruff (>=0.11.10,<0.12.0)
Requires-Dist: scikit-learn (>=1.6.1,<2.0.0)
Requires-Dist: scipy (>=1.15.3,<2.0.0)
Requires-Dist: seaborn (>=0.13.2,<0.14.0)
Requires-Dist: tables (>=3.10.2,<4.0.0)
Requires-Dist: tqdm (>=4.67.1,<5.0.0)
Requires-Dist: widgetsnbextension (>=4.0.14,<5.0.0)
Project-URL: Repository, https://github.com/maxvossel/elastory
